{"basics":{"name":"Giovani Valdrighi","label":"PhD Student","image":"","email":"giovani.valdrighi@ic.unicamp.br","phone":"","url":"https://giovanivaldrighi.github.io/","summary":"PhD student in Machine Learning at the Institute of Computing, University of Campinas. Researching on Trustworthy Machine Learning topics of Fairness and Explainability.","location":{"address":"","postalCode":"","city":"Campinas","countryCode":"BR","region":"São Paulo"},"profiles":[]},"work":[{"name":"Hub of Artificial Intelligence and Cognitive Architectures (H.IAAC), UNICAMP","position":"Researcher Assistant","url":"https://hiaac.unicamp.br/","startDate":"2023-08-01","endDate":"","summary":"Researcher assistant under the theme of AI for Finance, working on the development of trustworth Machine Learning models.","highlights":[]},{"name":"Visual Data Science Lab (VDS), FGV","position":"Researcher Assistant","url":"http://visualdslab.com/","startDate":"2020-08-01","endDate":"2024-05-01","summary":"Researcher assistant in the topic of visualization for spatiotemporal data.","highlights":[]},{"name":"Visualization Imaging and Data Analysis Center (VIDA), NYU","position":"Visiting Researcher","url":"https://vida.engineering.nyu.edu/","startDate":"2023-01-15","endDate":"2023-04-15","summary":"Visiting researcher in the topic of visualization for spatiotemporal data.","highlights":[]},{"name":"PICME/CNPq","position":"Undergraduate Researcher","url":"","startDate":"2018-08-01","endDate":"2020-07-01","summary":"Research scholarship with study of data science and causal inference.","highlights":[]}],"volunteer":[{"organization":"ACM FAccT 2024","position":"Student Volunteer","url":"https://facctconference.org/2024/","startDate":"2024-06-03","endDate":"2024-06-06","summary":"","highlights":[]},{"organization":"UNICAMP DETIC \"Perspectivas da IA Generativa\"","position":"Volunteer","url":"https://www.detic.unicamp.br/","startDate":"2024-11-28","endDate":"2024-11-28","summary":"","highlights":[]}],"education":[{"institution":"Institute of Computing, University of Campinas","location":"Campinas, Brazil","url":"https://ic.unicamp.br/","area":"Machine Learning","studyType":"PhD","startDate":"2023-08-01","endDate":"","score":"","courses":["Machine Learning"]},{"institution":"School of Applied Math, Getulio Vargas Foundation","location":"Rio de Janeiro, Brazil","url":"https://emap.fgv.br/","area":"Mathematical Modeling","studyType":"Master","startDate":"2022-03-01","endDate":"2024-06-01","score":"","courses":[]},{"institution":"School of Applied Math, Getulio Vargas Foundation","location":"Rio de Janeiro, Brazil","url":"https://emap.fgv.br/","area":"Applied Mathematics","studyType":"Bachelor","startDate":"2018-03-01","endDate":"2021-12-01","score":"","courses":[]}],"awards":[{"title":"Brazilian Public School Mathematics Olympiad (OBMEP)","date":"2011-2017","awarder":"National Institute of Pure and Applied Mathematics (IMPA)","url":"","summary":"Awarded with one gold, three silver and three bronze medals during the years of 2011 to 2017."},{"title":"Brazilian Astronomy and Astronautics Olympiad (OBA)","date":"2014","awarder":"Brazilian Society of Astronomy (SAB)","url":"","summary":"Awarded with a bronze medal."}],"certificates":[],"publications":[],"skills":[{"name":"Mathematics","level":"Master","icon":"fa-solid fa-hashtag","keywords":["Mathematical Modeling","Optimization","Probability"]},{"name":"Programming","level":"Master","icon":"fa-brands fa-python","keywords":["Python","C++","JavaScript","D3.js"]}],"languages":[{"language":"Portuguese","fluency":"Native speaker","icon":""},{"language":"English","fluency":"Fluent","icon":""}],"interests":[],"references":[],"projects":[]}